quark/__init__.py
quark/allocation_pool.py
quark/billing.py
quark/environment.py
quark/exceptions.py
quark/gunicorn_server.py
quark/ip_availability.py
quark/ipam.py
quark/network_strategy.py
quark/plugin.py
quark/plugin_views.py
quark/protocols.py
quark/quota_driver.py
quark/segment_allocations.py
quark/tags.py
quark/utils.py
quark/agent/README.md
quark/agent/__init__.py
quark/agent/agent.py
quark/agent/xapi.py
quark/agent/plugins/xenapi/contrib/build-rpm.sh
quark/agent/plugins/xenapi/contrib/rpmbuild/SPECS/quark-xen-plugins.spec
quark/agent/plugins/xenapi/etc/xapi.d/plugins/neutron_vif_flow
quark/api/__init__.py
quark/api/auth.py
quark/api/extensions/__init__.py
quark/api/extensions/diagnostics.py
quark/api/extensions/floatingip.py
quark/api/extensions/ip_addresses.py
quark/api/extensions/ip_availability.py
quark/api/extensions/ip_policies.py
quark/api/extensions/jobs.py
quark/api/extensions/mac_address_ranges.py
quark/api/extensions/networks_quark.py
quark/api/extensions/ports_quark.py
quark/api/extensions/routes.py
quark/api/extensions/scalingip.py
quark/api/extensions/segment_allocation_ranges.py
quark/api/extensions/subnets_quark.py
quark/cache/__init__.py
quark/cache/redis_base.py
quark/cache/security_groups_client.py
quark/db/__init__.py
quark/db/api.py
quark/db/custom_types.py
quark/db/ip_types.py
quark/db/models.py
quark/db/migration/__init__.py
quark/db/migration/alembic.ini
quark/db/migration/alembic/README.rst
quark/db/migration/alembic/__init__.py
quark/db/migration/alembic/cli.py
quark/db/migration/alembic/env.py
quark/db/migration/alembic/script.py.mako
quark/db/migration/alembic/versions/1284c81cf727_create_lswitch_and_lswitch_port_.py
quark/db/migration/alembic/versions/1664300cb03a_populate_first_last_ip_to_ippc.py
quark/db/migration/alembic/versions/1817eef6373c_initial_version.py
quark/db/migration/alembic/versions/1acd075bd7e1_add_first_last_ip_to_ippc.py
quark-1.0.0.dist-info/DESCRIPTION.rst
quark-1.0.0.dist-info/METADATA
quark-1.0.0.dist-info/RECORD
quark-1.0.0.dist-info/WHEEL
quark-1.0.0.dist-info/dependency_links.txt
quark-1.0.0.dist-info/entry_points.txt
quark-1.0.0.dist-info/metadata.json
quark-1.0.0.dist-info/pbr.json
quark-1.0.0.dist-info/top_level.txt
