Metadata-Version: 2.0
Name: quark
Version: 1.0.0
Summary: Neutron Plugin utilized by Rackspace to achieve large scale in Openstack. Quark developed on the ideas of segmentation and it being the source of truth for all things related to Neutron.
Home-page: http://github.com/openstack/quark
Author: Rackspace
Author-email: neutron@lists.rackspace.com
License: Apache-2
Platform: UNKNOWN
Classifier: Development Status :: 4 - Beta
Classifier: Environment :: Console
Classifier: Environment :: OpenStack
Classifier: Intended Audience :: Developers
Classifier: Intended Audience :: Information Technology
Classifier: License :: OSI Approved :: Apache Software License
Classifier: Operating System :: OS Independent
Classifier: Programming Language :: Python
Requires-Dist: SQLAlchemy (<1.1.0,>=1.0.10)
Requires-Dist: aiclib
Requires-Dist: alembic (>=0.8.4)
Requires-Dist: click (>=6.6)
Requires-Dist: docopt (==0.6.2)
Requires-Dist: gunicorn (==19.3.0)
Requires-Dist: mysql-python (==1.2.5)
Requires-Dist: neutron
Requires-Dist: neutron-lib (>=0.2.0)
Requires-Dist: oslo.concurrency (>=3.8.0)
Requires-Dist: oslo.config (>=3.10.0)
Requires-Dist: oslo.db (>=4.1.0)
Requires-Dist: oslo.middleware (>=3.0.0)
Requires-Dist: pymysql (==0.6.6)
Requires-Dist: twiceredis (>=2.0.0)
Requires-Dist: xenapi (==1.2)
Requires-Dist: Routes (!=2.3.0,!=2.0,>=1.12.3); (python_version!='2.7')
Requires-Dist: Routes (!=2.3.0,!=2.1,!=2.0,>=1.12.3); (python_version=='2.7')
